{"group_name":"16917","days":[{"weekday":1,"lessons":[{"subject":"Методология проектирования","type":"0","time_start":"16:35","time_end":"18:10","parity":"0","date_start":"02.09.2019","date_end":"19.01.2020","dates":null,"cluster_id":"29266","cluster_name":"16917","cluster_type":"ГРУППА","teachers":[{"teacher_name":"Завьялова Татьяна Арнольдовна","teacher_id":"13583"}],"auditories":[{"auditory_name":"1(20)","auditory_address":"ул. Никитина, 4","auditory_id":"1281"}]},{"subject":"Информационные технологии в творческой и проектной деятельности","type":"0","time_start":"18:25","time_end":"20:00","parity":"0","date_start":"02.09.2019","date_end":"05.01.2020","dates":null,"cluster_id":"29266","cluster_name":"16917","cluster_type":"ГРУППА","teachers":[{"teacher_name":"Бобков Станислав Павлович","teacher_id":"21875"}],"auditories":[{"auditory_name":"1(20)","auditory_address":"ул. Никитина, 4","auditory_id":"1281"}]}]},{"weekday":2,"lessons":[{"subject":"Методология проектирования","type":"0","time_start":"18:25","time_end":"20:00","parity":"0","date_start":"02.09.2019","date_end":"29.09.2019","dates":null,"cluster_id":"29266","cluster_name":"16917","cluster_type":"ГРУППА","teachers":[{"teacher_name":"Завьялова Татьяна Арнольдовна","teacher_id":"13583"}],"auditories":[{"auditory_name":"3(20)","auditory_address":"ул. Никитина, 4","auditory_id":"1283"}]},{"subject":"Практический синтез искусств","type":"3","time_start":"16:35","time_end":"18:10","parity":"0","date_start":"02.09.2019","date_end":"22.12.2019","dates":null,"cluster_id":"29266","cluster_name":"16917","cluster_type":"ГРУППА","teachers":[{"teacher_name":"Преображенский Г В","teacher_id":"23687"}],"auditories":[{"auditory_name":"3(20)","auditory_address":"ул. Никитина, 4","auditory_id":"1283"}]}]},{"weekday":3,"lessons":[{"subject":"Дизайн в современном обществе: решение актуальных проблем","type":"3","time_start":"18:25","time_end":"20:00","parity":"0","date_start":"02.09.2019","date_end":"19.01.2020","dates":null,"cluster_id":"29266","cluster_name":"16917","cluster_type":"ГРУППА","teachers":[{"teacher_name":"Галкин Дмитрий Владимирович","teacher_id":"12945"}],"auditories":[{"auditory_name":"3(20)","auditory_address":"ул. Никитина, 4","auditory_id":"1283"}]},{"subject":"Дизайн в современном обществе: решение актуальных проблем","type":"3","time_start":"16:35","time_end":"18:10","parity":"0","date_start":"02.09.2019","date_end":"19.01.2020","dates":null,"cluster_id":"29266","cluster_name":"16917","cluster_type":"ГРУППА","teachers":[{"teacher_name":"Галкин Дмитрий Владимирович","teacher_id":"12945"}],"auditories":[{"auditory_name":"3(20)","auditory_address":"ул. Никитина, 4","auditory_id":"1283"}]}]},{"weekday":4,"lessons":[{"subject":"Дизайн в современном обществе: решение актуальных проблем","type":"3","time_start":"18:25","time_end":"20:00","parity":"0","date_start":"02.09.2019","date_end":"13.10.2019","dates":null,"cluster_id":"29266","cluster_name":"16917","cluster_type":"ГРУППА","teachers":[{"teacher_name":"Галкин Дмитрий Владимирович","teacher_id":"12945"}],"auditories":[{"auditory_name":"233(1)","auditory_address":"пр. Ленина, 36","auditory_id":"2444"}]}]}]}