{"group_name":"201807","days":[{"weekday":1,"lessons":[{"subject":"Социология","type":"2","time_start":"10:35","time_end":"12:10","parity":"0","date_start":"02.09.2019","date_end":"03.11.2019","dates":null,"cluster_id":"31414","cluster_name":"209/8/7-1","cluster_type":"СВОДНЫЙ ПОТОК","teachers":[{"teacher_name":"Карнаухова Наталья Андреевна","teacher_id":"13927"}],"auditories":[{"auditory_name":"222(4)","auditory_address":"Московский тракт, 8","auditory_id":"445"}]},{"subject":"Практика по получению первичных профессиональных умений и навыков (профильные мастерские)","type":"0","time_start":"14:45","time_end":"16:20","parity":"0","date_start":"02.09.2019","date_end":"29.09.2019","dates":null,"cluster_id":"31432","cluster_name":"201807Б","cluster_type":"ПОДГРУППА","teachers":[{"teacher_name":"Бычкова Марина Николаевна","teacher_id":"12711"}],"auditories":[{"auditory_name":"528(4)","auditory_address":"Московский тракт, 8","auditory_id":"381"}]},{"subject":"Основы теории коммуникации","type":"2","time_start":"12:25","time_end":"14:00","parity":"0","date_start":"02.09.2019","date_end":"22.09.2019","dates":null,"cluster_id":"31372","cluster_name":"201807","cluster_type":"ГРУППА","teachers":[{"teacher_name":"Окушова Гульнафист Алтаевна","teacher_id":"15305"}],"auditories":[{"auditory_name":"519(4)","auditory_address":"Московский тракт, 8","auditory_id":"378"}]},{"subject":"Практика по получению первичных профессиональных умений и навыков (профильные мастерские)","type":"0","time_start":"14:45","time_end":"16:20","parity":"0","date_start":"02.09.2019","date_end":"29.12.2019","dates":null,"cluster_id":"31434","cluster_name":"201807П","cluster_type":"ПОДГРУППА","teachers":[{"teacher_name":"Полянская Екатерина Викторовна","teacher_id":"15567"}],"auditories":[{"auditory_name":"408(4)","auditory_address":"Московский тракт, 8","auditory_id":"3482"}]}]},{"weekday":2,"lessons":[{"subject":"Практика по получению первичных профессиональных умений и навыков (профильные мастерские)","type":"0","time_start":"20:15","time_end":"21:50","parity":"0","date_start":"02.09.2019","date_end":"29.12.2019","dates":null,"cluster_id":"31432","cluster_name":"201807Б","cluster_type":"ПОДГРУППА","teachers":[{"teacher_name":"Бычкова Марина Николаевна","teacher_id":"12711"}],"auditories":[{"auditory_name":"510(4)","auditory_address":"Московский тракт, 8","auditory_id":"376"}]},{"subject":"Практика по получению первичных профессиональных умений и навыков (профильные мастерские)","type":"0","time_start":"14:45","time_end":"16:20","parity":"0","date_start":"02.09.2019","date_end":"06.10.2019","dates":null,"cluster_id":"31435","cluster_name":"201807Н","cluster_type":"ПОДГРУППА","teachers":[{"teacher_name":"Носова Снежана Сергеевна","teacher_id":"15259"}],"auditories":[{"auditory_name":"511(4)","auditory_address":"Московский тракт, 8","auditory_id":"377"}]},{"subject":"Политология","type":"2","time_start":"16:35","time_end":"18:10","parity":"0","date_start":"02.09.2019","date_end":"27.10.2019","dates":null,"cluster_id":"31405","cluster_name":"2018-2","cluster_type":"СВОДНЫЙ ПОТОК","teachers":[{"teacher_name":"Постол Владимир Иванович","teacher_id":"15613"}],"auditories":[{"auditory_name":"129(4)","auditory_address":"Московский тракт, 8","auditory_id":"441"}]},{"subject":"Элективные курсы по физической культуре и спорту","type":"0","time_start":"08:45","time_end":"10:20","parity":"0","date_start":"02.09.2019","date_end":"29.12.2019","dates":null,"cluster_id":"31392","cluster_name":"2018","cluster_type":"ПОТОК","teachers":[{"teacher_name":"Радаева Светлана Викторовна","teacher_id":"15695"}],"auditories":[{"auditory_name":"920(14)","auditory_address":"Дом спорта, пр. Ленина, 36","auditory_id":"951"}]},{"subject":"Практика по получению первичных профессиональных умений и навыков (профильные мастерские)","type":"0","time_start":"12:25","time_end":"14:00","parity":"0","date_start":"02.09.2019","date_end":"06.10.2019","dates":null,"cluster_id":"31435","cluster_name":"201807Н","cluster_type":"ПОДГРУППА","teachers":[{"teacher_name":"Носова Снежана Сергеевна","teacher_id":"15259"}],"auditories":[{"auditory_name":"511(4)","auditory_address":"Московский тракт, 8","auditory_id":"377"}]},{"subject":"Иностранный язык","type":"0","time_start":"18:25","time_end":"20:00","parity":"0","date_start":"02.09.2019","date_end":"08.12.2019","dates":null,"cluster_id":"31430","cluster_name":"201807-1","cluster_type":"ПОДГРУППА","teachers":[{"teacher_name":"Полянская Екатерина Викторовна","teacher_id":"15567"}],"auditories":[{"auditory_name":"510(4)","auditory_address":"Московский тракт, 8","auditory_id":"376"}]}]},{"weekday":3,"lessons":[{"subject":"Кризисные коммуникации","type":"2","time_start":"12:25","time_end":"14:00","parity":"0","date_start":"02.09.2019","date_end":"27.10.2019","dates":null,"cluster_id":"31372","cluster_name":"201807","cluster_type":"ГРУППА","teachers":[{"teacher_name":"Гужова Ирина Викторовна","teacher_id":"13189"}],"auditories":[{"auditory_name":"519(4)","auditory_address":"Московский тракт, 8","auditory_id":"378"}]},{"subject":"Практика по получению первичных профессиональных умений и навыков (профильные мастерские)","type":"0","time_start":"14:45","time_end":"16:20","parity":"0","date_start":"02.09.2019","date_end":"29.09.2019","dates":null,"cluster_id":"31434","cluster_name":"201807П","cluster_type":"ПОДГРУППА","teachers":[{"teacher_name":"Полянская Екатерина Викторовна","teacher_id":"15567"}],"auditories":[{"auditory_name":"408(4)","auditory_address":"Московский тракт, 8","auditory_id":"3482"}]},{"subject":"Основы интегрированных коммуникаций","type":"3","time_start":"10:35","time_end":"12:10","parity":"0","date_start":"14.10.2019","date_end":"27.10.2019","dates":null,"cluster_id":"31372","cluster_name":"201807","cluster_type":"ГРУППА","teachers":[{"teacher_name":"Бычкова Марина Николаевна","teacher_id":"12711"}],"auditories":[{"auditory_name":"519(4)","auditory_address":"Московский тракт, 8","auditory_id":"378"}]},{"subject":"Основы интегрированных коммуникаций","type":"2","time_start":"10:35","time_end":"12:10","parity":"0","date_start":"02.09.2019","date_end":"13.10.2019","dates":null,"cluster_id":"31372","cluster_name":"201807","cluster_type":"ГРУППА","teachers":[{"teacher_name":"Камарова Назира Адиловна","teacher_id":"22589"}],"auditories":[{"auditory_name":"519(4)","auditory_address":"Московский тракт, 8","auditory_id":"378"}]}]},{"weekday":4,"lessons":[{"subject":"Правовое регулирование в PR и рекламе","type":"0","time_start":"14:45","time_end":"16:20","parity":"0","date_start":"30.09.2019","date_end":"27.10.2019","dates":null,"cluster_id":"31372","cluster_name":"201807","cluster_type":"ГРУППА","teachers":[{"teacher_name":"Лапов Артем Евгеньевич","teacher_id":"23565"}],"auditories":[{"auditory_name":"536(4)","auditory_address":"Московский тракт, 8","auditory_id":"384"}]},{"subject":"Правовое регулирование в PR и рекламе","type":"0","time_start":"12:25","time_end":"14:00","parity":"0","date_start":"30.09.2019","date_end":"27.10.2019","dates":null,"cluster_id":"31372","cluster_name":"201807","cluster_type":"ГРУППА","teachers":[{"teacher_name":"Лапов Артем Евгеньевич","teacher_id":"23565"}],"auditories":[{"auditory_name":"536(4)","auditory_address":"Московский тракт, 8","auditory_id":"384"}]}]},{"weekday":5,"lessons":[{"subject":"Кризисные коммуникации","type":"0","time_start":"14:45","time_end":"16:20","parity":"0","date_start":"14.10.2019","date_end":"29.12.2019","dates":null,"cluster_id":"31372","cluster_name":"201807","cluster_type":"ГРУППА","teachers":[{"teacher_name":"Гужова Ирина Викторовна","teacher_id":"13189"}],"auditories":[{"auditory_name":"519(4)","auditory_address":"Московский тракт, 8","auditory_id":"378"}]},{"subject":"Практика по получению первичных профессиональных умений и навыков (профильные мастерские)","type":"0","time_start":"16:35","time_end":"18:10","parity":"0","date_start":"02.09.2019","date_end":"29.12.2019","dates":null,"cluster_id":"31433","cluster_name":"201807К","cluster_type":"ПОДГРУППА","teachers":[{"teacher_name":"Карнаухова Наталья Андреевна","teacher_id":"13927"}],"auditories":[{"auditory_name":"511(4)","auditory_address":"Московский тракт, 8","auditory_id":"377"}]},{"subject":"Практика по получению первичных профессиональных умений и навыков (профильные мастерские)","type":"0","time_start":"18:25","time_end":"20:00","parity":"0","date_start":"02.09.2019","date_end":"29.09.2019","dates":null,"cluster_id":"31433","cluster_name":"201807К","cluster_type":"ПОДГРУППА","teachers":[{"teacher_name":"Карнаухова Наталья Андреевна","teacher_id":"13927"}],"auditories":[{"auditory_name":"511(4)","auditory_address":"Московский тракт, 8","auditory_id":"377"}]}]},{"weekday":6,"lessons":[{"subject":"Иностранный язык","type":"0","time_start":"14:45","time_end":"16:20","parity":"0","date_start":"02.09.2019","date_end":"08.12.2019","dates":null,"cluster_id":"31431","cluster_name":"201807-2","cluster_type":"ПОДГРУППА","teachers":[{"teacher_name":"Полянская Екатерина Викторовна","teacher_id":"15567"}],"auditories":[{"auditory_name":"510(4)","auditory_address":"Московский тракт, 8","auditory_id":"376"}]},{"subject":"Основы теории коммуникации","type":"2","time_start":"12:25","time_end":"14:00","parity":"0","date_start":"02.09.2019","date_end":"20.10.2019","dates":null,"cluster_id":"31372","cluster_name":"201807","cluster_type":"ГРУППА","teachers":[{"teacher_name":"Окушова Гульнафист Алтаевна","teacher_id":"15305"}],"auditories":[{"auditory_name":"519(4)","auditory_address":"Московский тракт, 8","auditory_id":"378"}]},{"subject":"Основы теории коммуникации","type":"0","time_start":"12:25","time_end":"14:00","parity":"0","date_start":"21.10.2019","date_end":"29.12.2019","dates":null,"cluster_id":"31372","cluster_name":"201807","cluster_type":"ГРУППА","teachers":[{"teacher_name":"Окушова Гульнафист Алтаевна","teacher_id":"15305"}],"auditories":[{"auditory_name":"519(4)","auditory_address":"Московский тракт, 8","auditory_id":"378"}]},{"subject":"Элективные курсы по физической культуре и спорту","type":"0","time_start":"10:35","time_end":"12:10","parity":"0","date_start":"02.09.2019","date_end":"29.12.2019","dates":null,"cluster_id":"31392","cluster_name":"2018","cluster_type":"ПОТОК","teachers":[{"teacher_name":"Радаева Светлана Викторовна","teacher_id":"15695"}],"auditories":[{"auditory_name":"920(14)","auditory_address":"Дом спорта, пр. Ленина, 36","auditory_id":"951"}]}]}]}