{"group_name":"02705","days":[{"weekday":1,"lessons":[{"subject":"Гидрохимия","type":"1","time_start":"14:45","time_end":"16:20","parity":"0","date_start":"15.04.2019","date_end":"19.05.2019","dates":null,"cluster_id":"24733","cluster_name":"02705а","cluster_type":"ПОДГРУППА","teachers":[{"teacher_name":"Наумова Людмила Борисовна","teacher_id":"15135"}],"auditories":[{"auditory_name":"325(6)","auditory_address":"ул. А.Иванова, 49","auditory_id":"70"}]},{"subject":"Гидрохимия","type":"1","time_start":"14:45","time_end":"16:20","parity":"0","date_start":"18.02.2019","date_end":"17.03.2019","dates":null,"cluster_id":"24733","cluster_name":"02705а","cluster_type":"ПОДГРУППА","teachers":[{"teacher_name":"Шумар Светлана Викторовна","teacher_id":"17039"}],"auditories":[{"auditory_name":"314(6)","auditory_address":"ул. А.Иванова, 49","auditory_id":"71"}]},{"subject":"Иностранный язык","type":"0","time_start":"12:25","time_end":"14:00","parity":"0","date_start":"10.09.2018","date_end":"21.10.2018","dates":null,"cluster_id":"24734","cluster_name":"02705б","cluster_type":"ПОДГРУППА","teachers":[{"teacher_name":"Шатурная Елена Алексеевна","teacher_id":"16905"}],"auditories":[{"auditory_name":"48(2)","auditory_address":"пр. Ленина, 36к2","auditory_id":"362"}]},{"subject":"Иностранный язык","type":"0","time_start":"12:25","time_end":"14:00","parity":"0","date_start":"22.10.2018","date_end":"25.11.2018","dates":null,"cluster_id":"24734","cluster_name":"02705б","cluster_type":"ПОДГРУППА","teachers":[{"teacher_name":"Шатурная Елена Алексеевна","teacher_id":"16905"}],"auditories":[{"auditory_name":"48(2)","auditory_address":"пр. Ленина, 36к2","auditory_id":"362"}]},{"subject":"Философия","type":"2","time_start":"08:45","time_end":"10:20","parity":"0","date_start":"03.09.2018","date_end":"16.12.2018","dates":null,"cluster_id":"24726","cluster_name":"027","cluster_type":"ПОТОК","teachers":[{"teacher_name":"Буковская Наталья Васильевна","teacher_id":"12613"}],"auditories":[{"auditory_name":"302(2)","auditory_address":"пр. Ленина, 36к2","auditory_id":"415"}]},{"subject":"Иностранный язык","type":"0","time_start":"12:25","time_end":"14:00","parity":"0","date_start":"10.09.2018","date_end":"30.12.2018","dates":null,"cluster_id":"24733","cluster_name":"02705а","cluster_type":"ПОДГРУППА","teachers":[{"teacher_name":"Стуканова Ольга Борисовна","teacher_id":"16223"}],"auditories":[{"auditory_name":"201(6)","auditory_address":"ул. А.Иванова, 49","auditory_id":"426"}]},{"subject":"Гидрохимия","type":"1","time_start":"12:25","time_end":"14:00","parity":"0","date_start":"15.04.2019","date_end":"19.05.2019","dates":null,"cluster_id":"24733","cluster_name":"02705а","cluster_type":"ПОДГРУППА","teachers":[{"teacher_name":"Наумова Людмила Борисовна","teacher_id":"15135"}],"auditories":[{"auditory_name":"325(6)","auditory_address":"ул. А.Иванова, 49","auditory_id":"70"}]},{"subject":"Гидробиология и водная экология","type":"1","time_start":"14:45","time_end":"16:20","parity":"0","date_start":"19.11.2018","date_end":"30.12.2018","dates":null,"cluster_id":"24730","cluster_name":"02705","cluster_type":"ГРУППА","teachers":[{"teacher_name":"Вершинин Дмитрий Александрович","teacher_id":"12777"}],"auditories":[{"auditory_name":"312(6)","auditory_address":"ул. А.Иванова, 49","auditory_id":"1162"}]},{"subject":"Гидрометрия и техника безопасности","type":"1","time_start":"14:45","time_end":"16:20","parity":"0","date_start":"18.02.2019","date_end":"02.06.2019","dates":null,"cluster_id":"24734","cluster_name":"02705б","cluster_type":"ПОДГРУППА","teachers":[{"teacher_name":"Паромов Владимир Валериянович","teacher_id":"15393"}],"auditories":[{"auditory_name":"217(6)","auditory_address":"ул. А.Иванова, 49","auditory_id":"214"}]},{"subject":"Иностранный язык","type":"0","time_start":"12:25","time_end":"14:00","parity":"0","date_start":"18.02.2019","date_end":"24.02.2019","dates":null,"cluster_id":"24734","cluster_name":"02705б","cluster_type":"ПОДГРУППА","teachers":[{"teacher_name":"Шатурная Елена Алексеевна","teacher_id":"16905"}],"auditories":[{"auditory_name":"218(6)","auditory_address":"ул. А.Иванова, 49","auditory_id":"219"}]},{"subject":"Гидрометрия и техника безопасности","type":"2","time_start":"10:35","time_end":"12:10","parity":"0","date_start":"01.10.2018","date_end":"30.12.2018","dates":null,"cluster_id":"24730","cluster_name":"02705","cluster_type":"ГРУППА","teachers":[{"teacher_name":"Паромов Владимир Валериянович","teacher_id":"15393"}],"auditories":[{"auditory_name":"208(6)","auditory_address":"ул. А.Иванова, 49","auditory_id":"213"}]},{"subject":"Гидрология суши","type":"1","time_start":"18:25","time_end":"20:00","parity":"0","date_start":"18.02.2019","date_end":"02.06.2019","dates":null,"cluster_id":"24733","cluster_name":"02705а","cluster_type":"ПОДГРУППА","teachers":[{"teacher_name":"Тарасов Александр Сергеевич","teacher_id":"19687"}],"auditories":[{"auditory_name":"208(6)","auditory_address":"ул. А.Иванова, 49","auditory_id":"213"}]},{"subject":"Иностранный язык","type":"0","time_start":"12:25","time_end":"14:00","parity":"0","date_start":"26.11.2018","date_end":"30.12.2018","dates":null,"cluster_id":"24734","cluster_name":"02705б","cluster_type":"ПОДГРУППА","teachers":[{"teacher_name":"Шатурная Елена Алексеевна","teacher_id":"16905"}],"auditories":[{"auditory_name":"212(6)","auditory_address":"ул. А.Иванова, 49","auditory_id":"429"}]},{"subject":"Философия","type":"2","time_start":"08:45","time_end":"10:20","parity":"0","date_start":"24.12.2018","date_end":"30.12.2018","dates":null,"cluster_id":"24726","cluster_name":"027","cluster_type":"ПОТОК","teachers":[{"teacher_name":"Буковская Наталья Васильевна","teacher_id":"12613"}],"auditories":[{"auditory_name":"302(2)","auditory_address":"пр. Ленина, 36к2","auditory_id":"415"}]},{"subject":"Гидрохимия","type":"1","time_start":"12:25","time_end":"14:00","parity":"0","date_start":"18.02.2019","date_end":"17.03.2019","dates":null,"cluster_id":"24733","cluster_name":"02705а","cluster_type":"ПОДГРУППА","teachers":[{"teacher_name":"Шумар Светлана Викторовна","teacher_id":"17039"}],"auditories":[{"auditory_name":"314(6)","auditory_address":"ул. А.Иванова, 49","auditory_id":"71"}]},{"subject":"Гидробиология и водная экология","type":"1","time_start":"14:45","time_end":"16:20","parity":"0","date_start":"05.11.2018","date_end":"18.11.2018","dates":null,"cluster_id":"24730","cluster_name":"02705","cluster_type":"ГРУППА","teachers":[{"teacher_name":"Вершинин Дмитрий Александрович","teacher_id":"12777"}],"auditories":[{"auditory_name":"312(6)","auditory_address":"ул. А.Иванова, 49","auditory_id":"1162"}]},{"subject":"Иностранный язык","type":"0","time_start":"18:25","time_end":"20:00","parity":"0","date_start":"26.11.2018","date_end":"30.12.2018","dates":null,"cluster_id":"25585","cluster_name":"027-12357","cluster_type":"СВОДНЫЙ ПОТОК","teachers":[{"teacher_name":"Азарова Марина Валерьевна","teacher_id":"12049"}],"auditories":[{"auditory_name":"27(2)","auditory_address":"пр. Ленина, 36к2","auditory_id":"357"}]},{"subject":"Иностранный язык","type":"0","time_start":"18:25","time_end":"20:00","parity":"0","date_start":"10.09.2018","date_end":"25.11.2018","dates":null,"cluster_id":"25585","cluster_name":"027-12357","cluster_type":"СВОДНЫЙ ПОТОК","teachers":[{"teacher_name":"Азарова Марина Валерьевна","teacher_id":"12049"}],"auditories":[{"auditory_name":"27(2)","auditory_address":"пр. Ленина, 36к2","auditory_id":"357"}]},{"subject":"Гидрометрия и техника безопасности","type":"2","time_start":"16:35","time_end":"18:10","parity":"0","date_start":"18.02.2019","date_end":"02.06.2019","dates":null,"cluster_id":"24730","cluster_name":"02705","cluster_type":"ГРУППА","teachers":[{"teacher_name":"Паромов Владимир Валериянович","teacher_id":"15393"}],"auditories":[{"auditory_name":"108(6)","auditory_address":"ул. А.Иванова, 49","auditory_id":"424"}]}]},{"weekday":2,"lessons":[{"subject":"Физическая культура и спорт","type":"0","time_start":"14:45","time_end":"16:20","parity":"0","date_start":"24.12.2018","date_end":"30.12.2018","dates":null,"cluster_id":"25455","cluster_name":"027!","cluster_type":"СВОДНЫЙ ПОТОК","teachers":[{"teacher_name":"Черепанова Лилия Александровна","teacher_id":"16793"}],"auditories":[{"auditory_name":"902(14)","auditory_address":"Дом спорта, пр. Ленина, 36","auditory_id":"903"}]},{"subject":"Физическая культура","type":"0","time_start":"08:45","time_end":"10:20","parity":"0","date_start":"18.02.2019","date_end":"19.05.2019","dates":null,"cluster_id":"24726","cluster_name":"027","cluster_type":"ПОТОК","teachers":[{"teacher_name":"Черепанова Лилия Александровна","teacher_id":"16793"}],"auditories":[{"auditory_name":"902(14)","auditory_address":"Дом спорта, пр. Ленина, 36","auditory_id":"903"}]},{"subject":"Гидрохимия","type":"2","time_start":"14:45","time_end":"16:20","parity":"0","date_start":"18.02.2019","date_end":"14.04.2019","dates":null,"cluster_id":"24730","cluster_name":"02705","cluster_type":"ГРУППА","teachers":[{"teacher_name":"Шумар Светлана Викторовна","teacher_id":"17039"}],"auditories":[{"auditory_name":"212(6)","auditory_address":"ул. А.Иванова, 49","auditory_id":"429"}]},{"subject":"Иностранный язык","type":"0","time_start":"18:25","time_end":"20:00","parity":"0","date_start":"18.02.2019","date_end":"12.05.2019","dates":null,"cluster_id":"28837","cluster_name":"271б2б5б6б","cluster_type":"СВОДНЫЙ ПОТОК","teachers":[{"teacher_name":"Азарова Марина Валерьевна","teacher_id":"12049"}],"auditories":[{"auditory_name":"26(2)","auditory_address":"пр. Ленина, 36к2","auditory_id":"356"}]},{"subject":"Философия","type":"2","time_start":"14:45","time_end":"16:20","parity":"0","date_start":"17.12.2018","date_end":"23.12.2018","dates":null,"cluster_id":"24726","cluster_name":"027","cluster_type":"ПОТОК","teachers":[{"teacher_name":"Буковская Наталья Васильевна","teacher_id":"12613"}],"auditories":[{"auditory_name":"332(2)","auditory_address":"пр. Ленина, 36к2","auditory_id":"417"}]},{"subject":"Гидрохимия","type":"2","time_start":"14:45","time_end":"16:20","parity":"0","date_start":"15.04.2019","date_end":"02.06.2019","dates":null,"cluster_id":"24730","cluster_name":"02705","cluster_type":"ГРУППА","teachers":[{"teacher_name":"Наумова Людмила Борисовна","teacher_id":"15135"}],"auditories":[{"auditory_name":"212(6)","auditory_address":"ул. А.Иванова, 49","auditory_id":"429"}]},{"subject":"Информатика","type":"1","time_start":"10:35","time_end":"12:10","parity":"0","date_start":"18.02.2019","date_end":"02.06.2019","dates":null,"cluster_id":"24733","cluster_name":"02705а","cluster_type":"ПОДГРУППА","teachers":[{"teacher_name":"Дубровская Лариса Ивановна","teacher_id":"13393"}],"auditories":[{"auditory_name":"217(6)","auditory_address":"ул. А.Иванова, 49","auditory_id":"214"}]},{"subject":"Информатика","type":"1","time_start":"12:25","time_end":"14:00","parity":"0","date_start":"18.02.2019","date_end":"02.06.2019","dates":null,"cluster_id":"24734","cluster_name":"02705б","cluster_type":"ПОДГРУППА","teachers":[{"teacher_name":"Дубровская Лариса Ивановна","teacher_id":"13393"}],"auditories":[{"auditory_name":"217(6)","auditory_address":"ул. А.Иванова, 49","auditory_id":"214"}]},{"subject":"Физическая культура и спорт","type":"0","time_start":"14:45","time_end":"16:20","parity":"0","date_start":"03.09.2018","date_end":"16.12.2018","dates":null,"cluster_id":"25455","cluster_name":"027!","cluster_type":"СВОДНЫЙ ПОТОК","teachers":[{"teacher_name":"Черепанова Лилия Александровна","teacher_id":"16793"}],"auditories":[{"auditory_name":"902(14)","auditory_address":"Дом спорта, пр. Ленина, 36","auditory_id":"903"}]},{"subject":"Математика","type":"0","time_start":"12:25","time_end":"14:00","parity":"0","date_start":"26.11.2018","date_end":"30.12.2018","dates":null,"cluster_id":"24730","cluster_name":"02705","cluster_type":"ГРУППА","teachers":[{"teacher_name":"Малютина Александра Николаевна","teacher_id":"14789"}],"auditories":[{"auditory_name":"218(6)","auditory_address":"ул. А.Иванова, 49","auditory_id":"219"}]},{"subject":"Математика","type":"0","time_start":"12:25","time_end":"14:00","parity":"0","date_start":"01.10.2018","date_end":"25.11.2018","dates":null,"cluster_id":"24730","cluster_name":"02705","cluster_type":"ГРУППА","teachers":[{"teacher_name":"Малютина Александра Николаевна","teacher_id":"14789"}],"auditories":[{"auditory_name":"218(6)","auditory_address":"ул. А.Иванова, 49","auditory_id":"219"}]},{"subject":"Математика","type":"2","time_start":"10:35","time_end":"12:10","parity":"0","date_start":"03.09.2018","date_end":"25.11.2018","dates":null,"cluster_id":"24728","cluster_name":"027-35","cluster_type":"СВОДНЫЙ ПОТОК","teachers":[{"teacher_name":"Малютина Александра Николаевна","teacher_id":"14789"}],"auditories":[{"auditory_name":"215(6)","auditory_address":"ул. А.Иванова, 49","auditory_id":"218"}]},{"subject":"Философия","type":"3","time_start":"08:45","time_end":"10:20","parity":"0","date_start":"08.10.2018","date_end":"30.12.2018","dates":null,"cluster_id":"24730","cluster_name":"02705","cluster_type":"ГРУППА","teachers":[{"teacher_name":"Бахтиярова Елена Захаровна","teacher_id":"12361"}],"auditories":[{"auditory_name":"108(6)","auditory_address":"ул. А.Иванова, 49","auditory_id":"424"}]},{"subject":"Гидрология суши","type":"2","time_start":"16:35","time_end":"18:10","parity":"0","date_start":"18.02.2019","date_end":"02.06.2019","dates":null,"cluster_id":"28774","cluster_name":"027-35!!","cluster_type":"СВОДНЫЙ ПОТОК","teachers":[{"teacher_name":"Тарасов Александр Сергеевич","teacher_id":"19687"}],"auditories":[{"auditory_name":"108(6)","auditory_address":"ул. А.Иванова, 49","auditory_id":"424"}]}]},{"weekday":3,"lessons":[{"subject":"Гидрометрия и техника безопасности","type":"1","time_start":"16:35","time_end":"18:10","parity":"0","date_start":"29.10.2018","date_end":"30.12.2018","dates":null,"cluster_id":"24733","cluster_name":"02705а","cluster_type":"ПОДГРУППА","teachers":[{"teacher_name":"Паромов Владимир Валериянович","teacher_id":"15393"}],"auditories":[{"auditory_name":"208(6)","auditory_address":"ул. А.Иванова, 49","auditory_id":"213"}]},{"subject":"Информатика","type":"1","time_start":"14:45","time_end":"16:20","parity":"0","date_start":"03.09.2018","date_end":"04.11.2018","dates":null,"cluster_id":"24734","cluster_name":"02705б","cluster_type":"ПОДГРУППА","teachers":[{"teacher_name":"Дубровская Лариса Ивановна","teacher_id":"13393"}],"auditories":[{"auditory_name":"217(6)","auditory_address":"ул. А.Иванова, 49","auditory_id":"214"}]},{"subject":"Иностранный язык","type":"0","time_start":"14:45","time_end":"16:20","parity":"0","date_start":"18.02.2019","date_end":"17.03.2019","dates":null,"cluster_id":"24734","cluster_name":"02705б","cluster_type":"ПОДГРУППА","teachers":[{"teacher_name":"Шатурная Елена Алексеевна","teacher_id":"16905"}],"auditories":[{"auditory_name":"212(6)","auditory_address":"ул. А.Иванова, 49","auditory_id":"429"}]},{"subject":"Иностранный язык","type":"0","time_start":"14:45","time_end":"16:20","parity":"0","date_start":"18.03.2019","date_end":"12.05.2019","dates":null,"cluster_id":"24734","cluster_name":"02705б","cluster_type":"ПОДГРУППА","teachers":[{"teacher_name":"Шатурная Елена Алексеевна","teacher_id":"16905"}],"auditories":[{"auditory_name":"212(6)","auditory_address":"ул. А.Иванова, 49","auditory_id":"429"}]},{"subject":"Информатика","type":"2","time_start":"12:25","time_end":"14:00","parity":"0","date_start":"03.09.2018","date_end":"25.11.2018","dates":null,"cluster_id":"24728","cluster_name":"027-35","cluster_type":"СВОДНЫЙ ПОТОК","teachers":[{"teacher_name":"Дубровская Лариса Ивановна","teacher_id":"13393"}],"auditories":[{"auditory_name":"108(6)","auditory_address":"ул. А.Иванова, 49","auditory_id":"424"}]},{"subject":"Философия","type":"3","time_start":"08:45","time_end":"10:20","parity":"0","date_start":"01.10.2018","date_end":"07.10.2018","dates":null,"cluster_id":"24730","cluster_name":"02705","cluster_type":"ГРУППА","teachers":[{"teacher_name":"Бахтиярова Елена Захаровна","teacher_id":"12361"}],"auditories":[{"auditory_name":"20(2)","auditory_address":"пр. Ленина, 36к2","auditory_id":"862"}]},{"subject":"Гидрометрия и техника безопасности","type":"1","time_start":"14:45","time_end":"16:20","parity":"0","date_start":"29.10.2018","date_end":"30.12.2018","dates":null,"cluster_id":"24733","cluster_name":"02705а","cluster_type":"ПОДГРУППА","teachers":[{"teacher_name":"Паромов Владимир Валериянович","teacher_id":"15393"}],"auditories":[{"auditory_name":"208(6)","auditory_address":"ул. А.Иванова, 49","auditory_id":"213"}]},{"subject":"Гидробиология и водная экология","type":"2","time_start":"10:35","time_end":"12:10","parity":"0","date_start":"03.09.2018","date_end":"30.12.2018","dates":null,"cluster_id":"24730","cluster_name":"02705","cluster_type":"ГРУППА","teachers":[{"teacher_name":"Вершинин Дмитрий Александрович","teacher_id":"12777"}],"auditories":[{"auditory_name":"208(6)","auditory_address":"ул. А.Иванова, 49","auditory_id":"213"}]},{"subject":"Математика","type":"2","time_start":"16:35","time_end":"18:10","parity":"0","date_start":"18.02.2019","date_end":"12.05.2019","dates":null,"cluster_id":"24728","cluster_name":"027-35","cluster_type":"СВОДНЫЙ ПОТОК","teachers":[{"teacher_name":"Малютина Александра Николаевна","teacher_id":"14789"}],"auditories":[{"auditory_name":"109(6)","auditory_address":"ул. А.Иванова, 49","auditory_id":"425"}]},{"subject":"Иностранный язык","type":"0","time_start":"14:45","time_end":"16:20","parity":"0","date_start":"18.02.2019","date_end":"12.05.2019","dates":null,"cluster_id":"24733","cluster_name":"02705а","cluster_type":"ПОДГРУППА","teachers":[{"teacher_name":"Стуканова Ольга Борисовна","teacher_id":"16223"}],"auditories":[{"auditory_name":"201(6)","auditory_address":"ул. А.Иванова, 49","auditory_id":"426"}]},{"subject":"Математика","type":"0","time_start":"18:25","time_end":"20:00","parity":"0","date_start":"18.03.2019","date_end":"02.06.2019","dates":null,"cluster_id":"24730","cluster_name":"02705","cluster_type":"ГРУППА","teachers":[{"teacher_name":"Малютина Александра Николаевна","teacher_id":"14789"}],"auditories":[{"auditory_name":"218(6)","auditory_address":"ул. А.Иванова, 49","auditory_id":"219"}]}]},{"weekday":4,"lessons":[{"subject":"Гидрометрия и техника безопасности","type":"1","time_start":"08:45","time_end":"10:20","parity":"0","date_start":"29.10.2018","date_end":"04.11.2018","dates":null,"cluster_id":"24734","cluster_name":"02705б","cluster_type":"ПОДГРУППА","teachers":[{"teacher_name":"Паромов Владимир Валериянович","teacher_id":"15393"}],"auditories":[{"auditory_name":"208(6)","auditory_address":"ул. А.Иванова, 49","auditory_id":"213"}]},{"subject":"Гидрохимия","type":"1","time_start":"10:35","time_end":"12:10","parity":"0","date_start":"15.04.2019","date_end":"19.05.2019","dates":null,"cluster_id":"24734","cluster_name":"02705б","cluster_type":"ПОДГРУППА","teachers":[{"teacher_name":"Наумова Людмила Борисовна","teacher_id":"15135"}],"auditories":[{"auditory_name":"325(6)","auditory_address":"ул. А.Иванова, 49","auditory_id":"70"}]},{"subject":"Гидрохимия","type":"1","time_start":"12:25","time_end":"14:00","parity":"0","date_start":"15.04.2019","date_end":"19.05.2019","dates":null,"cluster_id":"24734","cluster_name":"02705б","cluster_type":"ПОДГРУППА","teachers":[{"teacher_name":"Наумова Людмила Борисовна","teacher_id":"15135"}],"auditories":[{"auditory_name":"325(6)","auditory_address":"ул. А.Иванова, 49","auditory_id":"70"}]},{"subject":"Гидрохимия","type":"1","time_start":"16:35","time_end":"18:10","parity":"0","date_start":"18.02.2019","date_end":"17.03.2019","dates":null,"cluster_id":"24734","cluster_name":"02705б","cluster_type":"ПОДГРУППА","teachers":[{"teacher_name":"Шумар Светлана Викторовна","teacher_id":"17039"}],"auditories":[{"auditory_name":"314(6)","auditory_address":"ул. А.Иванова, 49","auditory_id":"71"}]},{"subject":"Гидрометрия и техника безопасности","type":"1","time_start":"10:35","time_end":"12:10","parity":"0","date_start":"29.10.2018","date_end":"04.11.2018","dates":null,"cluster_id":"24734","cluster_name":"02705б","cluster_type":"ПОДГРУППА","teachers":[{"teacher_name":"Паромов Владимир Валериянович","teacher_id":"15393"}],"auditories":[{"auditory_name":"208(6)","auditory_address":"ул. А.Иванова, 49","auditory_id":"213"}]},{"subject":"Гидрохимия","type":"1","time_start":"14:45","time_end":"16:20","parity":"0","date_start":"18.02.2019","date_end":"17.03.2019","dates":null,"cluster_id":"24734","cluster_name":"02705б","cluster_type":"ПОДГРУППА","teachers":[{"teacher_name":"Шумар Светлана Викторовна","teacher_id":"17039"}],"auditories":[{"auditory_name":"314(6)","auditory_address":"ул. А.Иванова, 49","auditory_id":"71"}]}]},{"weekday":5,"lessons":[{"subject":"Физика","type":"0","time_start":"12:25","time_end":"14:00","parity":"0","date_start":"01.10.2018","date_end":"28.10.2018","dates":null,"cluster_id":"24730","cluster_name":"02705","cluster_type":"ГРУППА","teachers":[{"teacher_name":"Толстик Александр Михайлович","teacher_id":"16399"}],"auditories":[{"auditory_name":"241(2)","auditory_address":"пр. Ленина, 36к2","auditory_id":"169"}]},{"subject":"Гидрология суши","type":"1","time_start":"14:45","time_end":"16:20","parity":"0","date_start":"18.02.2019","date_end":"17.03.2019","dates":null,"cluster_id":"24734","cluster_name":"02705б","cluster_type":"ПОДГРУППА","teachers":[{"teacher_name":"Тарасов Александр Сергеевич","teacher_id":"19687"}],"auditories":[{"auditory_name":"208(6)","auditory_address":"ул. А.Иванова, 49","auditory_id":"213"}]},{"subject":"Начальная медицинская подготовка","type":"2","time_start":"18:25","time_end":"20:00","parity":"0","date_start":"18.02.2019","date_end":"24.03.2019","dates":null,"cluster_id":"27278","cluster_name":"027-35М","cluster_type":"СВОДНЫЙ ПОТОК","teachers":[{"teacher_name":"Соловцова Наталия Анатольевна","teacher_id":"16139"}],"auditories":[{"auditory_name":"131(2)","auditory_address":"пр. Ленина, 36к2","auditory_id":"165"}]},{"subject":"Информатика","type":"2","time_start":"16:35","time_end":"18:10","parity":"0","date_start":"18.02.2019","date_end":"17.03.2019","dates":null,"cluster_id":"24728","cluster_name":"027-35","cluster_type":"СВОДНЫЙ ПОТОК","teachers":[{"teacher_name":"Волкова Марина Александровна","teacher_id":"12835"}],"auditories":[{"auditory_name":"215(6)","auditory_address":"ул. А.Иванова, 49","auditory_id":"218"}]},{"subject":"Начальная медицинская подготовка","type":"0","time_start":"10:35","time_end":"12:10","parity":"0","date_start":"25.03.2019","date_end":"31.03.2019","dates":null,"cluster_id":"27278","cluster_name":"027-35М","cluster_type":"СВОДНЫЙ ПОТОК","teachers":[{"teacher_name":"Соловцова Наталия Анатольевна","teacher_id":"16139"}],"auditories":[{"auditory_name":"1(3)","auditory_address":"пр. Ленина, 34","auditory_id":"402"}]},{"subject":"Иностранный язык","type":"0","time_start":"14:45","time_end":"16:20","parity":"0","date_start":"18.02.2019","date_end":"12.05.2019","dates":null,"cluster_id":"24733","cluster_name":"02705а","cluster_type":"ПОДГРУППА","teachers":[{"teacher_name":"Стуканова Ольга Борисовна","teacher_id":"16223"}],"auditories":[{"auditory_name":"315А(6)","auditory_address":"ул. А.Иванова, 49","auditory_id":"4302"}]},{"subject":"Гидрометрия и техника безопасности","type":"1","time_start":"12:25","time_end":"14:00","parity":"0","date_start":"18.02.2019","date_end":"17.03.2019","dates":null,"cluster_id":"24733","cluster_name":"02705а","cluster_type":"ПОДГРУППА","teachers":[{"teacher_name":"Паромов Владимир Валериянович","teacher_id":"15393"}],"auditories":[{"auditory_name":"217(6)","auditory_address":"ул. А.Иванова, 49","auditory_id":"214"}]},{"subject":"Гидрометрия и техника безопасности","type":"1","time_start":"14:45","time_end":"16:20","parity":"0","date_start":"05.11.2018","date_end":"30.12.2018","dates":null,"cluster_id":"24734","cluster_name":"02705б","cluster_type":"ПОДГРУППА","teachers":[{"teacher_name":"Паромов Владимир Валериянович","teacher_id":"15393"}],"auditories":[{"auditory_name":"208(6)","auditory_address":"ул. А.Иванова, 49","auditory_id":"213"}]},{"subject":"Физика","type":"2","time_start":"14:45","time_end":"16:20","parity":"0","date_start":"03.09.2018","date_end":"16.09.2018","dates":null,"cluster_id":"24728","cluster_name":"027-35","cluster_type":"СВОДНЫЙ ПОТОК","teachers":[{"teacher_name":"Потекаев Александр Иванович","teacher_id":"15617"}],"auditories":[{"auditory_name":"141(1)","auditory_address":"пр. Ленина, 36","auditory_id":"349"}]},{"subject":"Физика","type":"0","time_start":"16:35","time_end":"18:10","parity":"0","date_start":"29.10.2018","date_end":"18.11.2018","dates":null,"cluster_id":"24730","cluster_name":"02705","cluster_type":"ГРУППА","teachers":[{"teacher_name":"Толстик Александр Михайлович","teacher_id":"16399"}],"auditories":[{"auditory_name":"206(6)","auditory_address":"ул. А.Иванова, 49","auditory_id":"427"}]},{"subject":"Гидрология суши","type":"1","time_start":"14:45","time_end":"16:20","parity":"0","date_start":"20.05.2019","date_end":"02.06.2019","dates":null,"cluster_id":"24734","cluster_name":"02705б","cluster_type":"ПОДГРУППА","teachers":[{"teacher_name":"Тарасов Александр Сергеевич","teacher_id":"19687"}],"auditories":[{"auditory_name":"208(6)","auditory_address":"ул. А.Иванова, 49","auditory_id":"213"}]},{"subject":"Начальная медицинская подготовка","type":"0","time_start":"10:35","time_end":"12:10","parity":"0","date_start":"08.04.2019","date_end":"14.04.2019","dates":null,"cluster_id":"27278","cluster_name":"027-35М","cluster_type":"СВОДНЫЙ ПОТОК","teachers":[{"teacher_name":"Соловцова Наталия Анатольевна","teacher_id":"16139"}],"auditories":[{"auditory_name":"2(1)","auditory_address":"пр. Ленина, 36","auditory_id":"342"}]},{"subject":"Гидрометрия и техника безопасности","type":"1","time_start":"12:25","time_end":"14:00","parity":"0","date_start":"18.03.2019","date_end":"02.06.2019","dates":null,"cluster_id":"24733","cluster_name":"02705а","cluster_type":"ПОДГРУППА","teachers":[{"teacher_name":"Паромов Владимир Валериянович","teacher_id":"15393"}],"auditories":[{"auditory_name":"217(6)","auditory_address":"ул. А.Иванова, 49","auditory_id":"214"}]},{"subject":"Начальная медицинская подготовка","type":"0","time_start":"10:35","time_end":"12:10","parity":"0","date_start":"15.04.2019","date_end":"19.05.2019","dates":null,"cluster_id":"27278","cluster_name":"027-35М","cluster_type":"СВОДНЫЙ ПОТОК","teachers":[{"teacher_name":"Соловцова Наталия Анатольевна","teacher_id":"16139"}],"auditories":[{"auditory_name":"2(1)","auditory_address":"пр. Ленина, 36","auditory_id":"342"}]},{"subject":"Начальная медицинская подготовка","type":"0","time_start":"10:35","time_end":"12:10","parity":"0","date_start":"01.04.2019","date_end":"07.04.2019","dates":null,"cluster_id":"27278","cluster_name":"027-35М","cluster_type":"СВОДНЫЙ ПОТОК","teachers":[{"teacher_name":"Соловцова Наталия Анатольевна","teacher_id":"16139"}],"auditories":[{"auditory_name":"2(1)","auditory_address":"пр. Ленина, 36","auditory_id":"342"}]},{"subject":"Иностранный язык","type":"0","time_start":"14:45","time_end":"16:20","parity":"0","date_start":"08.04.2019","date_end":"12.05.2019","dates":null,"cluster_id":"24734","cluster_name":"02705б","cluster_type":"ПОДГРУППА","teachers":[{"teacher_name":"Шатурная Елена Алексеевна","teacher_id":"16905"}],"auditories":[{"auditory_name":"312(6)","auditory_address":"ул. А.Иванова, 49","auditory_id":"1162"}]},{"subject":"Иностранный язык","type":"0","time_start":"12:25","time_end":"14:00","parity":"0","date_start":"25.02.2019","date_end":"24.03.2019","dates":null,"cluster_id":"24734","cluster_name":"02705б","cluster_type":"ПОДГРУППА","teachers":[{"teacher_name":"Шатурная Елена Алексеевна","teacher_id":"16905"}],"auditories":[{"auditory_name":"526(4)","auditory_address":"Московский тракт, 8","auditory_id":"3402"}]},{"subject":"Гидрология суши","type":"1","time_start":"16:35","time_end":"18:10","parity":"0","date_start":"18.03.2019","date_end":"19.05.2019","dates":null,"cluster_id":"24734","cluster_name":"02705б","cluster_type":"ПОДГРУППА","teachers":[{"teacher_name":"Тарасов Александр Сергеевич","teacher_id":"19687"}],"auditories":[{"auditory_name":"215(6)","auditory_address":"ул. А.Иванова, 49","auditory_id":"218"}]},{"subject":"Иностранный язык","type":"0","time_start":"14:45","time_end":"16:20","parity":"0","date_start":"25.03.2019","date_end":"07.04.2019","dates":null,"cluster_id":"24734","cluster_name":"02705б","cluster_type":"ПОДГРУППА","teachers":[{"teacher_name":"Шатурная Елена Алексеевна","teacher_id":"16905"}],"auditories":[{"auditory_name":"208(6)","auditory_address":"ул. А.Иванова, 49","auditory_id":"213"}]},{"subject":"Гидрометрия и техника безопасности","type":"1","time_start":"12:25","time_end":"14:00","parity":"0","date_start":"05.11.2018","date_end":"30.12.2018","dates":null,"cluster_id":"24734","cluster_name":"02705б","cluster_type":"ПОДГРУППА","teachers":[{"teacher_name":"Паромов Владимир Валериянович","teacher_id":"15393"}],"auditories":[{"auditory_name":"312(6)","auditory_address":"ул. А.Иванова, 49","auditory_id":"1162"}]},{"subject":"Физика","type":"2","time_start":"14:45","time_end":"16:20","parity":"0","date_start":"17.09.2018","date_end":"04.11.2018","dates":null,"cluster_id":"24728","cluster_name":"027-35","cluster_type":"СВОДНЫЙ ПОТОК","teachers":[{"teacher_name":"Потекаев Александр Иванович","teacher_id":"15617"}],"auditories":[{"auditory_name":"428(2)","auditory_address":"пр. Ленина, 36к2","auditory_id":"423"}]}]},{"weekday":6,"lessons":[{"subject":"Гидробиология и водная экология","type":"1","time_start":"10:35","time_end":"12:10","parity":"0","date_start":"29.10.2018","date_end":"04.11.2018","dates":null,"cluster_id":"24730","cluster_name":"02705","cluster_type":"ГРУППА","teachers":[{"teacher_name":"Вершинин Дмитрий Александрович","teacher_id":"12777"}],"auditories":[{"auditory_name":"208(6)","auditory_address":"ул. А.Иванова, 49","auditory_id":"213"}]},{"subject":"Физическая культура","type":"0","time_start":"10:35","time_end":"12:10","parity":"0","date_start":"01.04.2019","date_end":"12.05.2019","dates":null,"cluster_id":"24726","cluster_name":"027","cluster_type":"ПОТОК","teachers":[{"teacher_name":"Черепанова Лилия Александровна","teacher_id":"16793"}],"auditories":[{"auditory_name":"902(14)","auditory_address":"Дом спорта, пр. Ленина, 36","auditory_id":"903"}]},{"subject":"Физическая культура","type":"0","time_start":"10:35","time_end":"12:10","parity":"0","date_start":"13.05.2019","date_end":"19.05.2019","dates":null,"cluster_id":"24726","cluster_name":"027","cluster_type":"ПОТОК","teachers":[{"teacher_name":"Черепанова Лилия Александровна","teacher_id":"16793"}],"auditories":[{"auditory_name":"902(14)","auditory_address":"Дом спорта, пр. Ленина, 36","auditory_id":"903"}]},{"subject":"Гидрометрия и техника безопасности","type":"2","time_start":"10:35","time_end":"12:10","parity":"0","date_start":"01.10.2018","date_end":"28.10.2018","dates":null,"cluster_id":"24730","cluster_name":"02705","cluster_type":"ГРУППА","teachers":[{"teacher_name":"Паромов Владимир Валериянович","teacher_id":"15393"}],"auditories":[{"auditory_name":"208(6)","auditory_address":"ул. А.Иванова, 49","auditory_id":"213"}]},{"subject":"Информатика","type":"1","time_start":"12:25","time_end":"14:00","parity":"0","date_start":"03.09.2018","date_end":"30.12.2018","dates":null,"cluster_id":"24733","cluster_name":"02705а","cluster_type":"ПОДГРУППА","teachers":[{"teacher_name":"Дубровская Лариса Ивановна","teacher_id":"13393"}],"auditories":[{"auditory_name":"217(6)","auditory_address":"ул. А.Иванова, 49","auditory_id":"214"}]},{"subject":"Иностранный язык","type":"0","time_start":"14:45","time_end":"16:20","parity":"0","date_start":"08.04.2019","date_end":"12.05.2019","dates":null,"cluster_id":"28837","cluster_name":"271б2б5б6б","cluster_type":"СВОДНЫЙ ПОТОК","teachers":[{"teacher_name":"Азарова Марина Валерьевна","teacher_id":"12049"}],"auditories":[{"auditory_name":"218(2)","auditory_address":"пр. Ленина, 36к2","auditory_id":"371"}]},{"subject":"Иностранный язык","type":"0","time_start":"10:35","time_end":"12:10","parity":"0","date_start":"25.02.2019","date_end":"31.03.2019","dates":null,"cluster_id":"28837","cluster_name":"271б2б5б6б","cluster_type":"СВОДНЫЙ ПОТОК","teachers":[{"teacher_name":"Азарова Марина Валерьевна","teacher_id":"12049"}],"auditories":[{"auditory_name":"306(4)","auditory_address":"Московский тракт, 8","auditory_id":"122"}]},{"subject":"Иностранный язык","type":"0","time_start":"14:45","time_end":"16:20","parity":"0","date_start":"18.02.2019","date_end":"24.02.2019","dates":null,"cluster_id":"27273","cluster_name":"027-125","cluster_type":"СВОДНЫЙ ПОТОК","teachers":[{"teacher_name":"Азарова Марина Валерьевна","teacher_id":"12049"}],"auditories":[{"auditory_name":"28(2)","auditory_address":"пр. Ленина, 36к2","auditory_id":"3742"}]},{"subject":"Иностранный язык","type":"0","time_start":"14:45","time_end":"16:20","parity":"0","date_start":"01.04.2019","date_end":"07.04.2019","dates":null,"cluster_id":"28837","cluster_name":"271б2б5б6б","cluster_type":"СВОДНЫЙ ПОТОК","teachers":[{"teacher_name":"Азарова Марина Валерьевна","teacher_id":"12049"}],"auditories":[{"auditory_name":"115(2)","auditory_address":"пр. Ленина, 36к2","auditory_id":"365"}]},{"subject":"Физическая культура","type":"0","time_start":"10:35","time_end":"12:10","parity":"0","date_start":"18.02.2019","date_end":"24.02.2019","dates":null,"cluster_id":"24726","cluster_name":"027","cluster_type":"ПОТОК","teachers":[{"teacher_name":"Черепанова Лилия Александровна","teacher_id":"16793"}],"auditories":[{"auditory_name":"902(14)","auditory_address":"Дом спорта, пр. Ленина, 36","auditory_id":"903"}]},{"subject":"Информатика","type":"1","time_start":"10:35","time_end":"12:10","parity":"0","date_start":"05.11.2018","date_end":"30.12.2018","dates":null,"cluster_id":"24734","cluster_name":"02705б","cluster_type":"ПОДГРУППА","teachers":[{"teacher_name":"Дубровская Лариса Ивановна","teacher_id":"13393"}],"auditories":[{"auditory_name":"217(6)","auditory_address":"ул. А.Иванова, 49","auditory_id":"214"}]},{"subject":"Физическая культура и спорт","type":"0","time_start":"14:45","time_end":"16:20","parity":"0","date_start":"03.09.2018","date_end":"30.12.2018","dates":null,"cluster_id":"25455","cluster_name":"027!","cluster_type":"СВОДНЫЙ ПОТОК","teachers":[{"teacher_name":"Черепанова Лилия Александровна","teacher_id":"16793"}],"auditories":[{"auditory_name":"902(14)","auditory_address":"Дом спорта, пр. Ленина, 36","auditory_id":"903"}]}]}]}