{"group_name":"037-д","days":[{"weekday":1,"lessons":[{"subject":"Предпринимательство","type":"2","time_start":"10:35","time_end":"12:10","parity":"0","date_start":"11.02.2019","date_end":"21.04.2019","dates":null,"cluster_id":"28218","cluster_name":"037идарзм","cluster_type":"СВОДНЫЙ ПОТОК","teachers":[{"teacher_name":"Рождественская Елена Михайловна","teacher_id":"22425"}],"auditories":[{"auditory_name":"222(4)","auditory_address":"Московский тракт, 8","auditory_id":"445"}]},{"subject":"Предпринимательство","type":"0","time_start":"12:25","time_end":"14:00","parity":"0","date_start":"18.02.2019","date_end":"21.04.2019","dates":null,"cluster_id":"28200","cluster_name":"037да!","cluster_type":"СВОДНЫЙ ПОТОК","teachers":[{"teacher_name":"Рождественская Елена Михайловна","teacher_id":"22425"}],"auditories":[{"auditory_name":"603Б(4)","auditory_address":"Московский тракт, 8","auditory_id":"388"}]},{"subject":"Предпринимательство","type":"0","time_start":"12:25","time_end":"14:00","parity":"0","date_start":"22.04.2019","date_end":"19.05.2019","dates":null,"cluster_id":"28200","cluster_name":"037да!","cluster_type":"СВОДНЫЙ ПОТОК","teachers":[{"teacher_name":"Рождественская Елена Михайловна","teacher_id":"22425"}],"auditories":[{"auditory_name":"603Б(4)","auditory_address":"Московский тракт, 8","auditory_id":"388"}]},{"subject":"Документная лингвистика","type":"2","time_start":"08:45","time_end":"10:20","parity":"0","date_start":"24.09.2018","date_end":"25.11.2018","dates":null,"cluster_id":"25608","cluster_name":"031705","cluster_type":"ГРУППА","teachers":[{"teacher_name":"Калиткина Галина Васильевна","teacher_id":"13865"}],"auditories":[{"auditory_name":"42(2)","auditory_address":"пр. Ленина, 36к2","auditory_id":"359"}]},{"subject":"Экономика","type":"2","time_start":"10:35","time_end":"12:10","parity":"0","date_start":"03.09.2018","date_end":"30.09.2018","dates":null,"cluster_id":"25598","cluster_name":"037","cluster_type":"СВОДНЫЙ ПОТОК","teachers":[{"teacher_name":"Соболева Екатерина Николаевна","teacher_id":"16115"}],"auditories":[{"auditory_name":"332(2)","auditory_address":"пр. Ленина, 36к2","auditory_id":"417"}]},{"subject":"Документы и архивы партий и общественных объединений России","type":"2","time_start":"08:45","time_end":"10:20","parity":"0","date_start":"25.02.2019","date_end":"21.04.2019","dates":null,"cluster_id":"25608","cluster_name":"031705","cluster_type":"ГРУППА","teachers":[{"teacher_name":"Ларьков Николай Семенович","teacher_id":"14541"}],"auditories":[{"auditory_name":"41(3)","auditory_address":"пр. Ленина, 34","auditory_id":"565"}]},{"subject":"История","type":"0","time_start":"14:45","time_end":"16:20","parity":"0","date_start":"22.10.2018","date_end":"23.12.2018","dates":null,"cluster_id":"25608","cluster_name":"031705","cluster_type":"ГРУППА","teachers":[{"teacher_name":"Осташова Евгения Андреевна","teacher_id":"17315"}],"auditories":[{"auditory_name":"41(3)","auditory_address":"пр. Ленина, 34","auditory_id":"565"}]},{"subject":"Документоведение","type":"0","time_start":"10:35","time_end":"12:10","parity":"0","date_start":"08.10.2018","date_end":"23.12.2018","dates":null,"cluster_id":"25608","cluster_name":"031705","cluster_type":"ГРУППА","teachers":[{"teacher_name":"Миркин Владимир Викторович","teacher_id":"14951"}],"auditories":[{"auditory_name":"7(3)","auditory_address":"пр. Ленина, 34","auditory_id":"561"}]},{"subject":"Иностранный язык","type":"0","time_start":"12:25","time_end":"14:00","parity":"0","date_start":"03.09.2018","date_end":"23.12.2018","dates":null,"cluster_id":"25608","cluster_name":"031705","cluster_type":"ГРУППА","teachers":[{"teacher_name":"Самофалова Елена Игоревна","teacher_id":"15905"}],"auditories":[{"auditory_name":"39(3)","auditory_address":"пр. Ленина, 34","auditory_id":"764"}]}]},{"weekday":2,"lessons":[{"subject":"Документная лингвистика","type":"0","time_start":"16:35","time_end":"18:10","parity":"0","date_start":"29.10.2018","date_end":"23.12.2018","dates":null,"cluster_id":"25608","cluster_name":"031705","cluster_type":"ГРУППА","teachers":[{"teacher_name":"Калиткина Галина Васильевна","teacher_id":"13865"}],"auditories":[{"auditory_name":"609(4)","auditory_address":"Московский тракт, 8","auditory_id":"395"}]}]},{"weekday":3,"lessons":[{"subject":"История","type":"0","time_start":"10:35","time_end":"12:10","parity":"0","date_start":"15.04.2019","date_end":"12.05.2019","dates":null,"cluster_id":"25608","cluster_name":"031705","cluster_type":"ГРУППА","teachers":[{"teacher_name":"Наумова Наталья Ивановна","teacher_id":"15137"}],"auditories":[{"auditory_name":"46(2)","auditory_address":"пр. Ленина, 36к2","auditory_id":"361"}]},{"subject":"Научно-исследовательский семинар","type":"0","time_start":"12:25","time_end":"14:00","parity":"0","date_start":"22.10.2018","date_end":"23.12.2018","dates":null,"cluster_id":"25608","cluster_name":"031705","cluster_type":"ГРУППА","teachers":[{"teacher_name":"Морев Владимир Алексеевич","teacher_id":"15041"}],"auditories":[{"auditory_name":"41(3)","auditory_address":"пр. Ленина, 34","auditory_id":"565"}]},{"subject":"Административное право","type":"2","time_start":"10:35","time_end":"12:10","parity":"0","date_start":"22.10.2018","date_end":"04.11.2018","dates":null,"cluster_id":"25608","cluster_name":"031705","cluster_type":"ГРУППА","teachers":[{"teacher_name":"Шушарина Елена Александровна","teacher_id":"17053"}],"auditories":[{"auditory_name":"528(4)","auditory_address":"Московский тракт, 8","auditory_id":"381"}]},{"subject":"Документы и архивы партий и общественных объединений России","type":"0","time_start":"12:25","time_end":"14:00","parity":"0","date_start":"08.04.2019","date_end":"02.06.2019","dates":null,"cluster_id":"25608","cluster_name":"031705","cluster_type":"ГРУППА","teachers":[{"teacher_name":"Ларьков Николай Семенович","teacher_id":"14541"}],"auditories":[{"auditory_name":"7(3)","auditory_address":"пр. Ленина, 34","auditory_id":"561"}]},{"subject":"Административное право","type":"0","time_start":"10:35","time_end":"12:10","parity":"0","date_start":"05.11.2018","date_end":"23.12.2018","dates":null,"cluster_id":"25608","cluster_name":"031705","cluster_type":"ГРУППА","teachers":[{"teacher_name":"Шушарина Елена Александровна","teacher_id":"17053"}],"auditories":[{"auditory_name":"528(4)","auditory_address":"Московский тракт, 8","auditory_id":"381"}]},{"subject":"Иностранный язык","type":"0","time_start":"14:45","time_end":"16:20","parity":"0","date_start":"17.09.2018","date_end":"23.12.2018","dates":null,"cluster_id":"25608","cluster_name":"031705","cluster_type":"ГРУППА","teachers":[{"teacher_name":"Самофалова Елена Игоревна","teacher_id":"15905"}],"auditories":[{"auditory_name":"40(3)","auditory_address":"пр. Ленина, 34","auditory_id":"769"}]},{"subject":"Научно-исследовательский семинар","type":"0","time_start":"12:25","time_end":"14:00","parity":"0","date_start":"03.09.2018","date_end":"23.09.2018","dates":null,"cluster_id":"25608","cluster_name":"031705","cluster_type":"ГРУППА","teachers":[{"teacher_name":"Морев Владимир Алексеевич","teacher_id":"15041"}],"auditories":[{"auditory_name":"41(3)","auditory_address":"пр. Ленина, 34","auditory_id":"565"}]},{"subject":"Административное право","type":"2","time_start":"10:35","time_end":"12:10","parity":"0","date_start":"03.09.2018","date_end":"23.09.2018","dates":null,"cluster_id":"25608","cluster_name":"031705","cluster_type":"ГРУППА","teachers":[{"teacher_name":"Шушарина Елена Александровна","teacher_id":"17053"}],"auditories":[{"auditory_name":"528(4)","auditory_address":"Московский тракт, 8","auditory_id":"381"}]},{"subject":"Административное право","type":"2","time_start":"16:35","time_end":"18:10","parity":"0","date_start":"24.09.2018","date_end":"21.10.2018","dates":null,"cluster_id":"25608","cluster_name":"031705","cluster_type":"ГРУППА","teachers":[{"teacher_name":"Шушарина Елена Александровна","teacher_id":"17053"}],"auditories":[{"auditory_name":"131(4)","auditory_address":"Московский тракт, 8","auditory_id":"443"}]},{"subject":"Иностранный язык","type":"0","time_start":"14:45","time_end":"16:20","parity":"0","date_start":"25.02.2019","date_end":"02.06.2019","dates":null,"cluster_id":"25608","cluster_name":"031705","cluster_type":"ГРУППА","teachers":[{"teacher_name":"Самофалова Елена Игоревна","teacher_id":"15905"}],"auditories":[{"auditory_name":"39(3)","auditory_address":"пр. Ленина, 34","auditory_id":"764"}]},{"subject":"Делопроизводственная практика","type":"0","time_start":"16:35","time_end":"18:10","parity":"0","date_start":"11.03.2019","date_end":"17.03.2019","dates":null,"cluster_id":"25608","cluster_name":"031705","cluster_type":"ГРУППА","teachers":[{"teacher_name":"Терентьева Екатерина Александровна","teacher_id":"23167"}],"auditories":[{"auditory_name":"28(3)","auditory_address":"пр. Ленина, 34","auditory_id":"410"}]},{"subject":"Иностранный язык","type":"0","time_start":"14:45","time_end":"16:20","parity":"0","date_start":"11.02.2019","date_end":"24.02.2019","dates":null,"cluster_id":"25608","cluster_name":"031705","cluster_type":"ГРУППА","teachers":[{"teacher_name":"Самофалова Елена Игоревна","teacher_id":"15905"}],"auditories":[{"auditory_name":"41(3)","auditory_address":"пр. Ленина, 34","auditory_id":"565"}]},{"subject":"Гражданское право","type":"0","time_start":"16:35","time_end":"18:10","parity":"0","date_start":"13.05.2019","date_end":"26.05.2019","dates":null,"cluster_id":"25608","cluster_name":"031705","cluster_type":"ГРУППА","teachers":[{"teacher_name":"Багрова Наталия Владиславовна","teacher_id":"12265"}],"auditories":[{"auditory_name":"100(4)","auditory_address":"Московский тракт, 8","auditory_id":"437"}]},{"subject":"Иностранный язык","type":"0","time_start":"14:45","time_end":"16:20","parity":"0","date_start":"03.09.2018","date_end":"16.09.2018","dates":null,"cluster_id":"25608","cluster_name":"031705","cluster_type":"ГРУППА","teachers":[{"teacher_name":"Самофалова Елена Игоревна","teacher_id":"15905"}],"auditories":[{"auditory_name":"40(3)","auditory_address":"пр. Ленина, 34","auditory_id":"769"}]},{"subject":"Физическая культура (элективный курс)","type":"0","time_start":"20:15","time_end":"21:50","parity":"0","date_start":"18.03.2019","date_end":"02.06.2019","dates":null,"cluster_id":"28215","cluster_name":"0317","cluster_type":"СВОДНЫЙ ПОТОК","teachers":[{"teacher_name":"Черданцева Раиса Геннадьевна","teacher_id":"16785"}],"auditories":[{"auditory_name":"903(14)","auditory_address":"Дом спорта, пр. Ленина, 36","auditory_id":"904"}]}]},{"weekday":4,"lessons":[{"subject":"Документоведение","type":"2","time_start":"12:25","time_end":"14:00","parity":"0","date_start":"03.09.2018","date_end":"25.11.2018","dates":null,"cluster_id":"25608","cluster_name":"031705","cluster_type":"ГРУППА","teachers":[{"teacher_name":"Быкова Татьяна Александровна","teacher_id":"12699"}],"auditories":[{"auditory_name":"41(3)","auditory_address":"пр. Ленина, 34","auditory_id":"565"}]},{"subject":"Предпринимательство","type":"0","time_start":"08:45","time_end":"10:20","parity":"0","date_start":"22.04.2019","date_end":"19.05.2019","dates":null,"cluster_id":"28200","cluster_name":"037да!","cluster_type":"СВОДНЫЙ ПОТОК","teachers":[{"teacher_name":"Рождественская Елена Михайловна","teacher_id":"22425"}],"auditories":[{"auditory_name":"27(3)","auditory_address":"пр. Ленина, 34","auditory_id":"409"}]},{"subject":"Научно-исследовательский семинар","type":"0","time_start":"12:25","time_end":"14:00","parity":"0","date_start":"11.02.2019","date_end":"02.06.2019","dates":null,"cluster_id":"25608","cluster_name":"031705","cluster_type":"ГРУППА","teachers":[{"teacher_name":"Быкова Татьяна Александровна","teacher_id":"12699"}],"auditories":[{"auditory_name":"41(3)","auditory_address":"пр. Ленина, 34","auditory_id":"565"}]},{"subject":"Иностранный язык","type":"0","time_start":"14:45","time_end":"16:20","parity":"0","date_start":"11.02.2019","date_end":"02.06.2019","dates":null,"cluster_id":"25608","cluster_name":"031705","cluster_type":"ГРУППА","teachers":[{"teacher_name":"Самофалова Елена Игоревна","teacher_id":"15905"}],"auditories":[{"auditory_name":"41(3)","auditory_address":"пр. Ленина, 34","auditory_id":"565"}]},{"subject":"Научно-исследовательский семинар","type":"0","time_start":"10:35","time_end":"12:10","parity":"0","date_start":"24.09.2018","date_end":"21.10.2018","dates":null,"cluster_id":"25608","cluster_name":"031705","cluster_type":"ГРУППА","teachers":[{"teacher_name":"Морев Владимир Алексеевич","teacher_id":"15041"}],"auditories":[{"auditory_name":"41(3)","auditory_address":"пр. Ленина, 34","auditory_id":"565"}]},{"subject":"Гражданское право","type":"0","time_start":"16:35","time_end":"18:10","parity":"0","date_start":"15.04.2019","date_end":"21.04.2019","dates":null,"cluster_id":"25608","cluster_name":"031705","cluster_type":"ГРУППА","teachers":[{"teacher_name":"Багрова Наталия Владиславовна","teacher_id":"12265"}],"auditories":[{"auditory_name":"614(4)","auditory_address":"Московский тракт, 8","auditory_id":"400"}]},{"subject":"История","type":"0","time_start":"10:35","time_end":"12:10","parity":"0","date_start":"04.03.2019","date_end":"14.04.2019","dates":null,"cluster_id":"25608","cluster_name":"031705","cluster_type":"ГРУППА","teachers":[{"teacher_name":"Наумова Наталья Ивановна","teacher_id":"15137"}],"auditories":[{"auditory_name":"41(3)","auditory_address":"пр. Ленина, 34","auditory_id":"565"}]},{"subject":"Русский язык и культура речи","type":"0","time_start":"10:35","time_end":"12:10","parity":"0","date_start":"29.10.2018","date_end":"23.12.2018","dates":null,"cluster_id":"25646","cluster_name":"037да","cluster_type":"СВОДНЫЙ ПОТОК","teachers":[{"teacher_name":"Вакансия ФилФ 3","teacher_id":"17663"}],"auditories":[{"auditory_name":"10(3)","auditory_address":"пр. Ленина, 34","auditory_id":"101"}]},{"subject":"Иностранный язык","type":"0","time_start":"14:45","time_end":"16:20","parity":"0","date_start":"03.09.2018","date_end":"16.09.2018","dates":null,"cluster_id":"25608","cluster_name":"031705","cluster_type":"ГРУППА","teachers":[{"teacher_name":"Самофалова Елена Игоревна","teacher_id":"15905"}],"auditories":[{"auditory_name":"40(3)","auditory_address":"пр. Ленина, 34","auditory_id":"769"}]},{"subject":"Гражданское право","type":"0","time_start":"16:35","time_end":"18:10","parity":"0","date_start":"22.04.2019","date_end":"12.05.2019","dates":null,"cluster_id":"25608","cluster_name":"031705","cluster_type":"ГРУППА","teachers":[{"teacher_name":"Багрова Наталия Владиславовна","teacher_id":"12265"}],"auditories":[{"auditory_name":"536(4)","auditory_address":"Московский тракт, 8","auditory_id":"384"}]},{"subject":"Физическая культура (элективный курс)","type":"0","time_start":"16:35","time_end":"18:10","parity":"0","date_start":"03.09.2018","date_end":"07.10.2018","dates":null,"cluster_id":"25598","cluster_name":"037","cluster_type":"СВОДНЫЙ ПОТОК","teachers":[{"teacher_name":"Черданцева Раиса Геннадьевна","teacher_id":"16785"}],"auditories":[{"auditory_name":"903(14)","auditory_address":"Дом спорта, пр. Ленина, 36","auditory_id":"904"}]},{"subject":"Физическая культура (элективный курс)","type":"0","time_start":"16:35","time_end":"18:10","parity":"0","date_start":"08.10.2018","date_end":"23.12.2018","dates":null,"cluster_id":"25598","cluster_name":"037","cluster_type":"СВОДНЫЙ ПОТОК","teachers":[{"teacher_name":"Черданцева Раиса Геннадьевна","teacher_id":"16785"}],"auditories":[{"auditory_name":"903(14)","auditory_address":"Дом спорта, пр. Ленина, 36","auditory_id":"904"}]},{"subject":"Физическая культура (элективный курс)","type":"0","time_start":"08:45","time_end":"10:20","parity":"0","date_start":"11.02.2019","date_end":"17.02.2019","dates":null,"cluster_id":"28215","cluster_name":"0317","cluster_type":"СВОДНЫЙ ПОТОК","teachers":[{"teacher_name":"Черданцева Раиса Геннадьевна","teacher_id":"16785"}],"auditories":[{"auditory_name":"903(14)","auditory_address":"Дом спорта, пр. Ленина, 36","auditory_id":"904"}]},{"subject":"Иностранный язык","type":"0","time_start":"14:45","time_end":"16:20","parity":"0","date_start":"17.09.2018","date_end":"23.12.2018","dates":null,"cluster_id":"25608","cluster_name":"031705","cluster_type":"ГРУППА","teachers":[{"teacher_name":"Самофалова Елена Игоревна","teacher_id":"15905"}],"auditories":[{"auditory_name":"40(3)","auditory_address":"пр. Ленина, 34","auditory_id":"769"}]}]},{"weekday":5,"lessons":[{"subject":"История","type":"2","time_start":"16:35","time_end":"18:10","parity":"0","date_start":"03.09.2018","date_end":"23.12.2018","dates":null,"cluster_id":"25608","cluster_name":"031705","cluster_type":"ГРУППА","teachers":[{"teacher_name":"Осташова Евгения Андреевна","teacher_id":"17315"}],"auditories":[{"auditory_name":"41(3)","auditory_address":"пр. Ленина, 34","auditory_id":"565"}]},{"subject":"Электронные способы организации данных","type":"0","time_start":"14:45","time_end":"16:20","parity":"0","date_start":"10.12.2018","date_end":"23.12.2018","dates":null,"cluster_id":"25796","cluster_name":"037ид","cluster_type":"СВОДНЫЙ ПОТОК","teachers":[{"teacher_name":"Меркулов Сергей Александрович","teacher_id":"14903"}],"auditories":[{"auditory_name":"7(3)","auditory_address":"пр. Ленина, 34","auditory_id":"561"}]},{"subject":"Электронные способы организации данных","type":"0","time_start":"14:45","time_end":"16:20","parity":"0","date_start":"24.09.2018","date_end":"09.12.2018","dates":null,"cluster_id":"25796","cluster_name":"037ид","cluster_type":"СВОДНЫЙ ПОТОК","teachers":[{"teacher_name":"Меркулов Сергей Александрович","teacher_id":"14903"}],"auditories":[{"auditory_name":"7(3)","auditory_address":"пр. Ленина, 34","auditory_id":"561"}]},{"subject":"Иностранный язык","type":"0","time_start":"16:35","time_end":"18:10","parity":"0","date_start":"11.02.2019","date_end":"02.06.2019","dates":null,"cluster_id":"25608","cluster_name":"031705","cluster_type":"ГРУППА","teachers":[{"teacher_name":"Самофалова Елена Игоревна","teacher_id":"15905"}],"auditories":[{"auditory_name":"612(4)","auditory_address":"Московский тракт, 8","auditory_id":"397"}]},{"subject":"Гражданское право","type":"2","time_start":"14:45","time_end":"16:20","parity":"0","date_start":"11.02.2019","date_end":"14.04.2019","dates":null,"cluster_id":"26359","cluster_name":"0317мд","cluster_type":"СВОДНЫЙ ПОТОК","teachers":[{"teacher_name":"Багрова Наталия Владиславовна","teacher_id":"12265"}],"auditories":[{"auditory_name":"100(4)","auditory_address":"Московский тракт, 8","auditory_id":"437"}]},{"subject":"История","type":"2","time_start":"18:25","time_end":"20:00","parity":"0","date_start":"11.02.2019","date_end":"19.05.2019","dates":null,"cluster_id":"25608","cluster_name":"031705","cluster_type":"ГРУППА","teachers":[{"teacher_name":"Наумова Наталья Ивановна","teacher_id":"15137"}],"auditories":[{"auditory_name":"41(3)","auditory_address":"пр. Ленина, 34","auditory_id":"565"}]}]},{"weekday":6,"lessons":[{"subject":"Электронные способы организации данных","type":"0","time_start":"10:35","time_end":"12:10","parity":"0","date_start":"10.12.2018","date_end":"23.12.2018","dates":null,"cluster_id":"25796","cluster_name":"037ид","cluster_type":"СВОДНЫЙ ПОТОК","teachers":[{"teacher_name":"Меркулов Сергей Александрович","teacher_id":"14903"}],"auditories":[{"auditory_name":"7(3)","auditory_address":"пр. Ленина, 34","auditory_id":"561"}]},{"subject":"Физическая культура (элективный курс)","type":"0","time_start":"12:25","time_end":"14:00","parity":"0","date_start":"18.03.2019","date_end":"02.06.2019","dates":null,"cluster_id":"28215","cluster_name":"0317","cluster_type":"СВОДНЫЙ ПОТОК","teachers":[{"teacher_name":"Черданцева Раиса Геннадьевна","teacher_id":"16785"}],"auditories":[{"auditory_name":"903(14)","auditory_address":"Дом спорта, пр. Ленина, 36","auditory_id":"904"}]},{"subject":"Экономика","type":"0","time_start":"12:25","time_end":"14:00","parity":"0","date_start":"01.10.2018","date_end":"09.12.2018","dates":null,"cluster_id":"25646","cluster_name":"037да","cluster_type":"СВОДНЫЙ ПОТОК","teachers":[{"teacher_name":"Соболева Екатерина Николаевна","teacher_id":"16115"}],"auditories":[{"auditory_name":"10(3)","auditory_address":"пр. Ленина, 34","auditory_id":"101"}]},{"subject":"Экономика","type":"2","time_start":"10:35","time_end":"12:10","parity":"0","date_start":"01.10.2018","date_end":"02.12.2018","dates":null,"cluster_id":"25598","cluster_name":"037","cluster_type":"СВОДНЫЙ ПОТОК","teachers":[{"teacher_name":"Соболева Екатерина Николаевна","teacher_id":"16115"}],"auditories":[{"auditory_name":"302(2)","auditory_address":"пр. Ленина, 36к2","auditory_id":"415"}]},{"subject":"Физическая культура (элективный курс)","type":"0","time_start":"12:25","time_end":"14:00","parity":"0","date_start":"25.02.2019","date_end":"17.03.2019","dates":null,"cluster_id":"28215","cluster_name":"0317","cluster_type":"СВОДНЫЙ ПОТОК","teachers":[{"teacher_name":"Черданцева Раиса Геннадьевна","teacher_id":"16785"}],"auditories":[{"auditory_name":"903(14)","auditory_address":"Дом спорта, пр. Ленина, 36","auditory_id":"904"}]},{"subject":"Физическая культура (элективный курс)","type":"0","time_start":"14:45","time_end":"16:20","parity":"0","date_start":"08.10.2018","date_end":"23.12.2018","dates":null,"cluster_id":"25598","cluster_name":"037","cluster_type":"СВОДНЫЙ ПОТОК","teachers":[{"teacher_name":"Черданцева Раиса Геннадьевна","teacher_id":"16785"}],"auditories":[{"auditory_name":"903(14)","auditory_address":"Дом спорта, пр. Ленина, 36","auditory_id":"904"}]},{"subject":"Экономика","type":"2","time_start":"10:35","time_end":"12:10","parity":"0","date_start":"03.09.2018","date_end":"30.09.2018","dates":null,"cluster_id":"25598","cluster_name":"037","cluster_type":"СВОДНЫЙ ПОТОК","teachers":[{"teacher_name":"Соболева Екатерина Николаевна","teacher_id":"16115"}],"auditories":[{"auditory_name":"302(2)","auditory_address":"пр. Ленина, 36к2","auditory_id":"415"}]}]}]}